django_audit_fields/__init__.py
django_audit_fields/admin.py
django_audit_fields/apps.py
django_audit_fields/constants.py
django_audit_fields/django_audit_fields.egg-info/PKG-INFO
django_audit_fields/django_audit_fields.egg-info/SOURCES.txt
django_audit_fields/django_audit_fields.egg-info/dependency_links.txt
django_audit_fields/django_audit_fields.egg-info/top_level.txt
django_audit_fields/fields/__init__.py
django_audit_fields/fields/hostname_modification_field.py
django_audit_fields/fields/userfield.py
django_audit_fields/fields/uuid_auto_field.py
django_audit_fields/locale/sw/LC_MESSAGES/django.mo
django_audit_fields/locale/sw/LC_MESSAGES/django.po
django_audit_fields/models/__init__.py
django_audit_fields/models/audit_model_mixin.py
django_audit_fields/models/audit_uuid_model_mixin.py
django_audit_fields/stubs.py
django_audit_fields-2.0.6.dist-info/licenses/LICENSE
django_audit_fields-2.0.6.dist-info/WHEEL
django_audit_fields-2.0.6.dist-info/METADATA
django_audit_fields-2.0.6.dist-info/RECORD
