Metadata-Version: 2.4
Name: django_audit_fields
Version: 2.0.6
Summary: Add model fields to track creation and modification dates, users and more on save
Keywords: django,clinicedc,edc,clinical trials,research,data management,esource
Author: Erik van Widenfelt
Author-email: Erik van Widenfelt <ew2789@gmail.com>
License-Expression: GPL-3.0-or-later
License-File: LICENSE
Classifier: Environment :: Web Environment
Classifier: Framework :: Django
Classifier: Framework :: Django :: 5.2
Classifier: Development Status :: 5 - Production/Stable
Classifier: Intended Audience :: Developers
Classifier: Intended Audience :: Science/Research
Classifier: Operating System :: OS Independent
Classifier: Programming Language :: Python :: 3.12
Classifier: Programming Language :: Python :: 3.13
Requires-Dist: django-revision>=2.0.0
Maintainer: Erik van Widenfelt
Maintainer-email: Erik van Widenfelt <ew2789@gmail.com>
Requires-Python: >=3.12
Project-URL: Changelog, https://github.com/erikvw/django-audit-fields/blob/main/CHANGES
Project-URL: Documentation, https://github.com/erikvw/django-audit-fields/docs
Project-URL: Homepage, https://github.com/erikvw/django-audit-fields
Project-URL: Repository, https://github.com/erikvw/django-audit-fields.git
